cloudbender/__init__.py
cloudbender/cli.py
cloudbender/connection.py
cloudbender/core.py
cloudbender/exceptions.py
cloudbender/hooks.py
cloudbender/jinja.py
cloudbender/pulumi.py
cloudbender/stack.py
cloudbender/stackgroup.py
cloudbender/utils.py
cloudbender/templates/__init__.py
cloudbender/templates/outputs.yaml
cloudbender/templates/stack-doc.md
cloudbender-0.22.2.dist-info/METADATA
cloudbender-0.22.2.dist-info/WHEEL
cloudbender-0.22.2.dist-info/entry_points.txt
cloudbender-0.22.2.dist-info/licenses/LICENSE.md
cloudbender-0.22.2.dist-info/RECORD
