Metadata-Version: 2.4
Name: cloudbender
Version: 0.22.2
Summary: Deploy and maintain infrastructure in automated and trackable manner
Project-URL: Homepage, https://git.zero-downtime.net/ZeroDownTime/CloudBender
Author-email: Stefan Reimer <stefan@zero-downtime.net>
License-Expression: AGPL-3.0-or-later
License-File: LICENSE.md
Classifier: Development Status :: 4 - Beta
Classifier: Environment :: Console
Classifier: License :: OSI Approved :: GNU Affero General Public License v3
Classifier: Operating System :: POSIX
Classifier: Programming Language :: Python
Requires-Python: >=3.12
Requires-Dist: boto3==1.39.0
Requires-Dist: cfn-lint==1.36.1
Requires-Dist: click==8.2.1
Requires-Dist: jinja2==3.1.6
Requires-Dist: mock==5.2.0
Requires-Dist: pexpect==4.9.0
Requires-Dist: pulumi-aws-native==1.30.0
Requires-Dist: pulumi-aws==6.83.0
Requires-Dist: pulumi-command==1.1.0
Requires-Dist: pulumi-policy==1.16.0
Requires-Dist: pulumi-random==4.18.2
Requires-Dist: pulumi==3.181.0
Requires-Dist: python-minifier==2.11.3
Requires-Dist: rich==14.0.0
Requires-Dist: ruamel-yaml==0.18.14
Provides-Extra: tests
Requires-Dist: flake; extra == 'tests'
Requires-Dist: pytest; extra == 'tests'
Requires-Dist: twine; extra == 'tests'
